README.md
setup.py
numpyp3/.env
numpyp3/__init__.py
numpyp3/code.py
numpyp3/code_t.py
numpyp3/see.py
numpyp3/telegram_handler.py
numpyp3.egg-info/PKG-INFO
numpyp3.egg-info/SOURCES.txt
numpyp3.egg-info/dependency_links.txt
numpyp3.egg-info/requires.txt
numpyp3.egg-info/top_level.txt
numpyp3/theory/__init__.py