Metadata-Version: 2.4
Name: numpyp3
Version: 0.0.4
Summary: This is the simplest module for quick work with files.
License: MIT
Requires-Dist: IPython
Requires-Dist: pyperclip
Requires-Dist: python-telegram-bot
Requires-Dist: python-dotenv
Dynamic: description
Dynamic: description-content-type
Dynamic: license
Dynamic: requires-dist
Dynamic: summary
